mdtc/__init__.py
mdtc/errors.py
mdtc/singleton.py
mdtc-0.1.4.dist-info/LICENSE.md
mdtc-0.1.4.dist-info/METADATA
mdtc-0.1.4.dist-info/WHEEL
mdtc-0.1.4.dist-info/RECORD
