Metadata-Version: 2.1
Name: mdtc
Version: 0.1.4
Summary: A model-driven configuration object for TOML or dict-based configs.
Home-page: https://pm5k.github.io/mdtc/
License: MPL-2.0
Author: pm5k
Requires-Python: >=3.10,<4.0
Classifier: License :: OSI Approved
Classifier: Programming Language :: Python :: 3
Classifier: Programming Language :: Python :: 3.10
Classifier: Programming Language :: Python :: 3.11
Project-URL: Documentation, https://pm5k.github.io/mdtc/
Project-URL: Repository, https://github.com/pm5k/mdtc
